Metadata-Version: 1.0
Name: stats-probalytics
Version: 1.3
Summary: Package for Gaussian and Binomial statistical distributions
Home-page: UNKNOWN
Author: Sumaiya Jelle Adan
Author-email: jellerayyann@gmail.com
License: UNKNOWN
Platform: UNKNOWN
